{
  "folk rock": 56, 
  "dance": 35, 
  "Lo-Fi": 30, 
  "power pop": 11, 
  "london": 19, 
  "heavy metal": 12, 
  "alternative": 189, 
  "classic rock": 91, 
  "alternative rock": 159, 
  "rock n roll": 21, 
  "baroque pop": 17, 
  "amazing": 15, 
  "easy listening": 21, 
  "Soundtrack": 21, 
  "piano": 21, 
  "Progressive": 11, 
  "Canadian": 11, 
  "songwriter": 13, 
  "jazz": 38, 
  "seen live": 188, 
  "singer-songwriter": 110, 
  "Favourites": 40, 
  "country rock": 13, 
  "Great Lyricists": 19, 
  "emo": 40, 
  "garage": 13, 
  "rock": 201, 
  "acoustic": 75, 
  "soft": 11, 
  "england": 40, 
  "female vocalist": 35, 
  "new wave": 52, 
  "blues": 49, 
  "Norway": 23, 
  "folk": 113, 
  "Britrock": 20, 
  "90s": 80, 
  "alternative pop": 15, 
  "Grunge": 16, 
  "want to see live": 15, 
  "electronica": 53, 
  "female vocalists": 56, 
  "Bands I have seen live": 11, 
  "genius": 24, 
  "british rock": 15, 
  "post-rock": 14, 
  "Mellow": 62, 
  "hard rock": 46, 
  "melancholy": 40, 
  "oldies": 32, 
  "70s": 40, 
  "guitar": 36, 
  "sexy": 14, 
  "trip-hop": 18, 
  "chamber pop": 14, 
  "legend": 20, 
  "melancholic": 23, 
  "country": 23, 
  "punk": 72, 
  "british": 78, 
  "american": 81, 
  "UK": 67, 
  "experimental": 72, 
  "beautiful": 51, 
  "norsk": 27, 
  "Favorite Artists": 16, 
  "americana": 26, 
  "male vocalists": 134, 
  "pop": 172, 
  "female": 35, 
  "brit pop": 14, 
  "glam rock": 11, 
  "electronic": 87, 
  "bergen": 11, 
  "Rock and Roll": 28, 
  "pop rock": 58, 
  "downtempo": 14, 
  "new york": 20, 
  "California": 15, 
  "psychedelic": 44, 
  "chillout": 64, 
  "happy": 15, 
  "relaxing": 11, 
  "relax": 12, 
  "soft rock": 31, 
  "female vocals": 22, 
  "funk": 11, 
  "chill": 43, 
  "Love": 58, 
  "brit rock": 28, 
  "Awesome": 43, 
  "soul": 25, 
  "scandinavian": 34, 
  "male vocalist": 19, 
  "fun": 20, 
  "indie pop": 115, 
  "Experimental Rock": 15, 
  "USA": 74, 
  "classic": 30, 
  "indie": 180, 
  "indietronica": 16, 
  "Female Voices": 19, 
  "sad": 11, 
  "00s": 127, 
  "Avant-Garde": 20, 
  "ambient": 26, 
  "singer songwriter": 24, 
  "britpop": 63, 
  "blues rock": 24, 
  "dream pop": 16, 
  "lounge": 11, 
  "post-punk": 54, 
  "Alt-country": 24, 
  "female vocal": 14, 
  "80s": 52, 
  "electro": 18, 
  "art rock": 22, 
  "punk rock": 31, 
  "indie folk": 33, 
  "Pop-Rock": 19, 
  "60s": 29, 
  "Garage Rock": 35, 
  "Favorite": 35, 
  "norwegian": 32, 
  "favorites": 107, 
  "Hip-Hop": 11, 
  "All": 16, 
  "Post-punk revival": 23, 
  "indie rock": 151, 
  "folk-rock": 23, 
  "Post punk": 13, 
  "metal": 27, 
  "Psychedelic Rock": 30, 
  "nordic": 15, 
  "english": 52, 
  "Progressive rock": 41
}