{
  "funk metal": 11,
  "classic": 99,
  "oldschool": 13,
  "mod": 18,
  "psychedelic pop": 32,
  "Grunge": 69,
  "shit": 34,
  "indietronica": 23,
  "Pop-punk": 26,
  "Altar of the Metal Gods": 12,
  "art rock": 60,
  "Officially Shit": 45,
  "latin": 16,
  "80's": 51,
  "prog": 21,
  "Retro": 13,
  "southern rap": 42,
  "south": 15,
  "1960s": 15,
  "dub": 15,
  "post rock": 15,
  "happy": 20,
  "party": 21,
  "psych": 17,
  "electronic": 187,
  "soft": 14,
  "brit rock": 21,
  "Southern Rock": 35,
  "male vocalists": 422,
  "atlanta": 23,
  "gangsta": 38,
  "Psychedelic Rock": 134,
  "britpop": 89,
  "prog rock": 23,
  "jecks": 14,
  "relax": 14,
  "spotify": 30,
  "Rock and Roll": 92,
  "industrial": 35,
  "synth pop": 25,
  "Canadian": 25,
  "r'n'b": 23,
  "sunshine pop": 17,
  "new york": 65,
  "folk rock": 89,
  "roots": 11,
  "Acid Rock": 28,
  "Pop-Rock": 65,
  "acoustic": 112,
  "Smooth Soul": 17,
  "NYC": 21,
  "Lo-Fi": 48,
  "Neo Soul": 12,
  "psychedelic folk": 14,
  "male vocalist": 66,
  "love songs": 17,
  "instrumental": 37,
  "synth": 11,
  "diva": 17,
  "west coast": 20,
  "glam": 28,
  "catchy": 12,
  "Disco": 47,
  "freak folk": 14,
  "hard rock": 248,
  "political": 30,
  "pop": 456,
  "hot": 20,
  "british rock": 21,
  "good": 12,
  "pop rock": 166,
  "rap": 135,
  "Garage Punk": 12,
  "old school": 48,
  "fun": 59,
  "east coast rap": 14,
  "funk": 146,
  "industrial metal": 12,
  "industrial rock": 14,
  "Old School soul": 14,
  "amazing": 47,
  "groove": 36,
  "Progressive": 65,
  "heavy metal": 95,
  "one hit wonder": 18,
  "Jam": 14,
  "soul": 175,
  "dance punk": 11,
  "G-funk": 13,
  "post-rock": 38,
  "ska": 25,
  "powerpop": 15,
  "san francisco": 19,
  "Rap US": 14,
  "70's": 37,
  "female vocalist": 64,
  "east coast hip-hop": 11,
  "guilty pleasure": 29,
  "Favourites": 37,
  "House": 24,
  "noise": 26,
  "brit pop": 12,
  "Progressive rock": 174,
  "Glam Metal": 25,
  "singer songwriter": 17,
  "piano": 25,
  "texas": 29,
  "legend": 63,
  "British Blues": 15,
  "emo": 147,
  "r&b": 99,
  "alternative rap": 11,
  "romantic": 26,
  "melodic rock": 21,
  "female vocal": 14,
  "blues rock": 115,
  "90's": 20,
  "Ballad": 14,
  "Recommended": 14,
  "proto-punk": 21,
  "Crap": 24,
  "power pop": 44,
  "Post Grunge": 11,
  "Great Lyricists": 20,
  "post-hardcore": 27,
  "Gangsta Rap": 57,
  "Boogie Rock": 11,
  "underground hip-hop": 26,
  "cool": 28,
  "sexy": 67,
  "Britrock": 20,
  "West Coast Rap": 14,
  "United States": 15,
  "post hardcore": 15,
  "00s": 276,
  "dance-pop": 20,
  "trippy": 13,
  "england": 69,
  "rapcore": 18,
  "electropop": 30,
  "Disney": 12,
  "baroque pop": 22,
  "60s rock": 13,
  "post-grunge": 29,
  "chillout": 104,
  "noise rock": 20,
  "Favorite Artists": 32,
  "death metal": 31,
  "alt rock": 21,
  "beautiful": 47,
  "old school rap": 11,
  "alternative metal": 42,
  "Mellow": 67,
  "bass": 15,
  "slow jams": 20,
  "motown": 31,
  "thrash metal": 21,
  "teen pop": 17,
  "vocal": 18,
  "english": 116,
  "florida": 12,
  "singer-songwriter": 208,
  "easy listening": 38,
  "hardcore": 98,
  "college rock": 19,
  "downtempo": 14,
  "chicago": 18,
  "Rap and Hip-Hop": 13,
  "Awesome": 109,
  "80s rock": 21,
  "Avant-Garde": 30,
  "Psychedelic Soul": 13,
  "Dirty South": 50,
  "indie folk": 26,
  "Gothic": 30,
  "alternative": 450,
  "80s Pop": 16,
  "Neo-Psychedelia": 32,
  "Guitar Hero": 12,
  "Post punk": 29,
  "Experimental Rock": 43,
  "punk rock": 142,
  "underground rap": 12,
  "lounge": 12,
  "Funk Rock": 28,
  "Psychedelia": 28,
  "pop punk": 39,
  "british": 162,
  "chamber pop": 14,
  "funny": 18,
  "georgia": 19,
  "Progressive metal": 23,
  "punk": 229,
  "USA": 386,
  "post-punk": 117,
  "emocore": 26,
  "rhythm and blues": 103,
  "arena rock": 18,
  "Female Voices": 15,
  "folk-rock": 40,
  "glam rock": 57,
  "Nu-metal": 11,
  "underrated": 12,
  "hiphop": 85,
  "British Psychedelia": 11,
  "rock": 603,
  "atmospheric": 14,
  "world": 11,
  "female vocalists": 104,
  "dream pop": 24,
  "Garage Rock": 68,
  "Love": 125,
  "indie rock": 231,
  "female vocals": 23,
  "garage": 39,
  "noise pop": 13,
  "avantgarde": 11,
  "Stoner Rock": 40,
  "hip-hop and rap": 16,
  "humor": 11,
  "rock n roll": 90,
  "synthpop": 34,
  "smooth": 31,
  "60s": 158,
  "Alt-country": 37,
  "americana": 38,
  "dark": 12,
  "dance": 172,
  "Scottish": 13,
  "black music": 13,
  "club": 16,
  "metalcore": 30,
  "UK": 138,
  "indie pop": 128,
  "album rock": 20,
  "new wave": 98,
  "seen live": 569,
  "crossover": 19,
  "hip hop": 137,
  "quiet storm": 20,
  "garage rock revival": 13,
  "british invasion": 19,
  "electro": 38,
  "sex": 11,
  "All": 103,
  "Nu Metal": 26,
  "Brutal Death Metal": 12,
  "Supergroup": 13,
  "woodstock": 20,
  "Post-punk revival": 23,
  "rap rock": 12,
  "blues": 165,
  "r and b": 49,
  "hardcore punk": 18,
  "Gothic Rock": 15,
  "AOR": 18,
  "60's": 50,
  "reggae": 36,
  "melancholy": 27,
  "soft rock": 90,
  "guitar": 95,
  "country rock": 28,
  "adult contemporary": 27,
  "1990s": 13,
  "East Coast": 15,
  "Black": 14,
  "groovy": 22,
  "folk": 145,
  "country": 39,
  "guitar virtuoso": 29,
  "acid jazz": 17,
  "Myjukebox": 18,
  "southern": 24,
  "90s": 279,
  "genius": 38,
  "hair metal": 27,
  "weird": 16,
  "Need to Rate": 12,
  "oldies": 164,
  "sweet": 16,
  "rnb": 173,
  "Guilty Pleasures": 24,
  "songwriter": 12,
  "los angeles": 39,
  "jazz": 118,
  "music": 15,
  "metal": 195,
  "bubblegum": 14,
  "trip-hop": 24,
  "experimental": 167,
  "westcoast": 11,
  "80s": 252,
  "detroit": 19,
  "hippie": 27,
  "american": 468,
  "Illinois": 13,
  "gay": 40,
  "new romantic": 11,
  "favorites": 224,
  "blues-rock": 46,
  "seattle": 18,
  "screamo": 38,
  "electronica": 85,
  "indie": 340,
  "Neo-Soul": 18,
  "scandinavian": 17,
  "dance pop": 12,
  "favourite": 11,
  "quirky": 15,
  "urban": 79,
  "Acoustic Rock": 16,
  "90s Rock": 14,
  "southern hip-hop": 28,
  "london": 30,
  "Favorite": 57,
  "singer-songwriters": 11,
  "Crunk": 34,
  "psychedelic": 172,
  "Hip-Hop": 170,
  "hardcore rap": 33,
  "Michigan": 13,
  "alternative rock": 311,
  "classic rock": 350,
  "goth": 17,
  "west coast hip-hop": 11,
  "space rock": 21,
  "melancholic": 19,
  "chill": 61,
  "Soundtrack": 75,
  "ATL": 15,
  "Gothic Metal": 11,
  "Punk-Rock": 16,
  "Fusion": 20,
  "finnish": 13,
  "canada": 19,
  "70s": 233,
  "female": 64,
  "classic soul": 12,
  "trance": 16,
  "ambient": 42,
  "funky": 58,
  "male": 30,
  "not emo": 20,
  "Blue-Eyed Soul": 12,
  "shoegaze": 30,
  "comedy": 20,
  "California": 99,
  "stoner": 14,
  "techno": 13
}