{
  "future jazz vibe": 19,
  "Lounge uptempo": 23,
  "irish": 13,
  "80s": 72,
  "deep": 11,
  "Ohms World": 14,
  "big beat": 16,
  "Espanol": 22,
  "cinematic": 17,
  "hard rock": 16,
  "relaxation": 17,
  "meditative": 28,
  "club": 39,
  "latino": 42,
  "hip hop": 46,
  "canada": 20,
  "Electrojazz": 12,
  "score": 15,
  "relaxing": 101,
  "Chillosophy": 56,
  "world fusion": 42,
  "chill with me": 22,
  "acoustic": 74,
  "composers": 23,
  "folk": 117,
  "World Music": 91,
  "vocal": 52,
  "serve chilled": 25,
  "chill-out": 17,
  "cool": 42,
  "india": 14,
  "Awesome": 28,
  "groovy": 19,
  "dark ambient": 33,
  "romantic": 42,
  "indie pop": 59,
  "jazzy flavoured": 22,
  "male vocalists": 99,
  "uutta jazziz": 20,
  "Eurovision": 11,
  "Ambient Techno": 23,
  "genius": 21,
  "sexy": 59,
  "chill906": 13,
  "guitar": 33,
  "synthpop": 21,
  "Canadian": 22,
  "tropical": 21,
  "melancholic": 33,
  "smooth lounge": 24,
  "portugu\u00eas": 15,
  "punk": 24,
  "groove": 45,
  "Indian": 13,
  "fun": 16,
  "Officially Shit": 12,
  "alternative lounge": 24,
  "jazzy downtempo vibe": 16,
  "jazzy down-tempo vibe": 16,
  "Portugal": 22,
  "fado": 17,
  "worldbeat": 13,
  "lusofonia": 14,
  "soul": 88,
  "my lounge room": 24,
  "swedish": 16,
  "electropcool": 19,
  "All": 141,
  "indietronica": 20,
  "Progressive rock": 39,
  "modern classical": 18,
  "jazzy": 26,
  "pop": 228,
  "Disco": 21,
  "medieval": 11,
  "portuguese": 27,
  "latin jazz": 13,
  "seen live": 307,
  "trip hop": 104,
  "Romantica": 15,
  "1st vine acid": 23,
  "folk rock": 18,
  "newage": 13,
  "spotify": 37,
  "Progressive House": 25,
  "Smooth Jazz": 29,
  "ibiza": 14,
  "90s": 149,
  "urban": 16,
  "tribal": 20,
  "chill chill": 24,
  "female vocalist": 103,
  "jazzy down tempo vibe": 15,
  "ninja tune": 18,
  "downtempo": 238,
  "Hip-Hop": 72,
  "breakbeat": 54,
  "piano": 45,
  "japanese": 15,
  "abstract": 15,
  "Best Of Downtempo": 25,
  "Soundtracks": 18,
  "death metal": 15,
  "asciiecho": 12,
  "relax": 113,
  "Bossa Nova": 28,
  "70s": 34,
  "60s": 18,
  "jazz-trip": 20,
  "enigmatic": 12,
  "electrocool": 19,
  "art rock": 16,
  "divas international": 11,
  "classic": 27,
  "buddamat": 19,
  "progressive trance": 22,
  "post-punk": 18,
  "traditional": 11,
  "easy listening": 132,
  "psychill": 18,
  "calm": 27,
  "downtempo vibe": 21,
  "puerto rico": 12,
  "singer-songwriter": 119,
  "synth": 15,
  "neo-classical": 13,
  "future jazz": 32,
  "american": 91,
  "Progressive": 30,
  "female vocal": 27,
  "best of down temp": 21,
  "darkwave": 14,
  "cafe del mar": 22,
  "african": 13,
  "noise": 12,
  "beautiful voice": 12,
  "10s": 21,
  "new wave": 31,
  "Jazzy vibes": 21,
  "jazzy female vocal": 16,
  "lounge chill": 24,
  "sweet downtempo": 24,
  "Drum n Bass": 27,
  "Hann with Gun": 12,
  "female": 92,
  "ambient": 312,
  "triphop": 20,
  "nujazz": 30,
  "groove lounge": 24,
  "indie rock": 70,
  "italian": 11,
  "happy": 12,
  "Asian": 16,
  "female vocalists": 198,
  "brazilian": 19,
  "dream pop": 32,
  "dream trance": 12,
  "australian": 11,
  "Favourites": 19,
  "amazing": 13,
  "ost": 16,
  "genre:downtempo": 23,
  "female artists": 12,
  "jungle": 16,
  "spanish": 47,
  "orchestral": 18,
  "male vocalist": 28,
  "british": 128,
  "down-tempo vibe": 21,
  "rock": 197,
  "lesser known yet streamable artists": 36,
  "electronic": 339,
  "dub": 61,
  "dark": 19,
  "female vocals": 58,
  "nu jazz": 81,
  "french": 28,
  "soft rock": 22,
  "chillout": 348,
  "dnb": 27,
  "indie": 174,
  "contemporary classical": 37,
  "spiritual": 26,
  "instrumental hip-hop": 14,
  "Lounge at home two": 23,
  "electronic dub": 19,
  "check out": 20,
  "lounge-radio": 12,
  "celtic": 33,
  "space": 22,
  "shoegaze": 22,
  "Dreamy": 46,
  "Space Ambient": 19,
  "modus": 18,
  "goa": 12,
  "eclectic": 17,
  "diva": 17,
  "nu jazz vibe": 19,
  "musica latina": 20,
  "Experimental Rock": 12,
  "chillounge1": 23,
  "post rock": 14,
  "nujazz vibe": 19,
  "cuba": 14,
  "composer": 37,
  "downtempo lounge": 21,
  "european": 15,
  "vocal downtempo": 20,
  "Gothic": 18,
  "underground hip-hop": 11,
  "chilllounge1": 23,
  "Best Of Down Tempo": 24,
  "england": 37,
  "favorit": 17,
  "jazzy trip": 20,
  "00s": 158,
  "favorites": 79,
  "favourite": 19,
  "german": 39,
  "Drum and bass": 49,
  "UK": 104,
  "Colombia": 12,
  "latina": 11,
  "hot": 11,
  "sensual": 12,
  "classic rock": 32,
  "Myjukebox": 29,
  "Soundtrack": 81,
  "minimalist": 11,
  "Smoothly Sexy Sounding": 24,
  "Ouahhhhh": 25,
  "melancholy": 38,
  "legend": 13,
  "world": 135,
  "chill": 226,
  "best of chill": 23,
  "tropcool": 24,
  "funky": 40,
  "soundscape": 21,
  "deep house": 31,
  "lounge jazz vibe": 21,
  "electro": 152,
  "dance": 170,
  "latin": 81,
  "glitch": 20,
  "Lo-Fi": 40,
  "alternative": 251,
  "Meditation": 28,
  "hiphop": 17,
  "drone": 22,
  "epic": 15,
  "Favorite": 35,
  "adult contemporary": 16,
  "Classical": 60,
  "germany": 24,
  "space music": 16,
  "alternative rock": 76,
  "Love": 63,
  "industrial": 29,
  "rnb": 25,
  "lounge downtempo": 24,
  "electronica": 292,
  "chill out": 100,
  "trip-hop": 189,
  "scandinavian": 16,
  "vocal-lounge": 20,
  "House": 104,
  "Mellow": 112,
  "Broken Beat": 12,
  "latin america": 12,
  "brazil": 12,
  "downtempo groove": 21,
  "new age": 111,
  "vocal trance": 17,
  "acid jazz": 106,
  "movie score composers": 13,
  "downtempo influence": 12,
  "atmospheric": 122,
  "lounge": 191,
  "emo": 28,
  "male": 24,
  "electropop": 27,
  "r&b": 13,
  "synth pop": 17,
  "served chilled": 23,
  "awesome downtempo": 24,
  "experimental": 178,
  "genre: downtempo": 24,
  "rap": 33,
  "blues": 37,
  "uuta jazzia": 20,
  "California": 13,
  "electronic lounge jazz": 21,
  "summer": 15,
  "gay": 20,
  "my-love": 25,
  "brasil": 14,
  "minimal": 41,
  "nu-jazz vibe": 19,
  "Fusion": 46,
  "psytrance": 17,
  "shit": 11,
  "espa\u00f1ol": 13,
  "cuban": 14,
  "beats": 31,
  "france": 18,
  "post-rock": 40,
  "english": 63,
  "new": 15,
  "deutsch": 13,
  "acid jazz vibe": 20,
  "oldies": 14,
  "party": 12,
  "acid lounge": 24,
  "Chillout Downtempo": 24,
  "techno": 70,
  "Dream": 18,
  "beautiful": 128,
  "sexy sounding": 24,
  "ethnic": 47,
  "idm": 85,
  "funk": 78,
  "psychedelic": 85,
  "neoclassical": 37,
  "Female Voices": 46,
  "peaceful": 23,
  "lounge at home tres": 24,
  "indie folk": 18,
  "melodic": 14,
  "USA": 68,
  "ethereal": 80,
  "lounge groove": 23,
  "salsa": 33,
  "lounge-tech": 23,
  "down tempo": 15,
  "reggae": 24,
  "contemporary instrumental": 18,
  "downbeat": 44,
  "Favorite Artists": 17,
  "avantgarde": 12,
  "britpop": 26,
  "pop rock": 46,
  "1st Vine": 25,
  "Pop-Rock": 15,
  "instrumental": 184,
  "new york": 12,
  "london": 19,
  "breaks": 28,
  "trance": 82,
  "acoustic groove": 24,
  "epic lounge": 23,
  "chillair": 24,
  "latin pop": 26,
  "Oriental": 11,
  "lounge electronic": 25,
  "downtempo influences": 23,
  "swing": 11,
  "film music": 11,
  "love songs": 14,
  "minimalism": 17,
  "smooth": 19,
  "uutta jazzia": 20,
  "jazz": 191,
  "space rock": 11,
  "ethnic fusion": 21,
  "hardcore": 16,
  "Avant-Garde": 36,
  "soft": 19,
  "Ballad": 27,
  "nu-jazz": 61,
  "dj": 26,
  "city lounge": 24,
  "lounge vibe": 22,
  "metal": 30,
  "deep ambient": 14
}