{
  "folk rock": 18, 
  "dance": 20, 
  "black metal": 54, 
  "heavy metal": 87, 
  "alternative": 97, 
  "classic rock": 87, 
  "alternative rock": 56, 
  "rock n roll": 27, 
  "Southern Rock": 13, 
  "art rock": 15, 
  "Rock and Roll": 21, 
  "german": 12, 
  "Melodic Death Metal": 35, 
  "Progressive": 34, 
  "rnb": 13, 
  "jazz": 40, 
  "seen live": 205, 
  "dark": 29, 
  "singer-songwriter": 39, 
  "atmospheric": 22, 
  "symphonic metal": 31, 
  "Norwegian Black Metal": 13, 
  "finnish": 50, 
  "emo": 13, 
  "rock": 166, 
  "acoustic": 17, 
  "england": 12, 
  "blues-rock": 34, 
  "female vocalist": 19, 
  "pagan metal": 18, 
  "guitar virtuoso": 18, 
  "new wave": 22, 
  "blues": 58, 
  "Norway": 23, 
  "folk": 40, 
  "90s": 57, 
  "finnish metal": 31, 
  "indie rock": 20, 
  "electronica": 22, 
  "electronic": 43, 
  "female vocalists": 35, 
  "Doom": 14, 
  "Progressive rock": 55, 
  "goth": 29, 
  "Symphonic Black Metal": 21, 
  "oldies": 34, 
  "finnish rock": 11, 
  "avantgarde": 12, 
  "70s": 57, 
  "guitar": 38, 
  "legend": 18, 
  "melancholic": 17, 
  "Power metal": 29, 
  "finland": 41, 
  "punk": 29, 
  "british": 46, 
  "Gothic Metal": 42, 
  "american": 73, 
  "Gothic": 43, 
  "Progressive metal": 49, 
  "UK": 37, 
  "Gothic Rock": 32, 
  "experimental": 44, 
  "industrial": 28, 
  "male vocalists": 72, 
  "pop": 58, 
  "melodic black metal": 30, 
  "thrash metal": 37, 
  "Black": 13, 
  "hard rock": 88, 
  "goth rock": 14, 
  "pop rock": 18, 
  "California": 11, 
  "ebm": 13, 
  "chillout": 17, 
  "industrial metal": 13, 
  "folk metal": 26, 
  "Suomi": 27, 
  "instrumental": 15, 
  "soft rock": 12, 
  "melodic metal": 37, 
  "industrial rock": 13, 
  "funk": 22, 
  "Avant-garde Metal": 12, 
  "dark electro": 11, 
  "death metal": 63, 
  "soul": 28, 
  "scandinavian": 19, 
  "Dark metal": 17, 
  "thrash": 15, 
  "USA": 62, 
  "classic": 25, 
  "indie": 46, 
  "viking metal": 19, 
  "Extreme Metal": 12, 
  "darkwave": 28, 
  "00s": 29, 
  "Avant-Garde": 14, 
  "ambient": 17, 
  "doom metal": 34, 
  "blues rock": 54, 
  "synthpop": 17, 
  "Stoner Rock": 11, 
  "post-punk": 17, 
  "80s": 80, 
  "electro": 14, 
  "rhythm and blues": 22, 
  "punk rock": 11, 
  "speed metal": 22, 
  "60s": 38, 
  "Garage Rock": 11, 
  "norwegian": 23, 
  "favorites": 23, 
  "psychedelic": 46, 
  "All": 22, 
  "Female fronted metal": 15, 
  "alternative metal": 13, 
  "metal": 133, 
  "synth pop": 11, 
  "Psychedelic Rock": 37, 
  "english": 22, 
  "epic metal": 13
}