{
  "japanese": 27,
  "underrated": 32,
  "show tunes": 11,
  "electronica": 260,
  "welsh": 12,
  "modern classical": 18,
  "Favourite bands": 13,
  "Need to Rate": 20,
  "r&b": 76,
  "musicals": 28,
  "new": 16,
  "female vocal": 92,
  "Hip-Hop": 104,
  "contemporary classical": 37,
  "post-grunge": 15,
  "50s": 57,
  "contemporary jazz": 12,
  "scandinavian": 33,
  "post rock": 13,
  "jazzy": 24,
  "ecto": 15,
  "funny": 25,
  "Fusion": 29,
  "check out": 34,
  "alt rock": 11,
  "piano": 122,
  "new jersey": 11,
  "indie rock": 384,
  "Classical": 93,
  "girls with guitars": 13,
  "male vocalist": 121,
  "actor": 24,
  "Love": 221,
  "fun": 83,
  "legend": 96,
  "good music": 13,
  "everything": 14,
  "Officially Shit": 31,
  "Soundtrack": 228,
  "lounge": 101,
  "Neo-Soul": 26,
  "composers": 61,
  "trip-hop": 91,
  "chill": 141,
  "<3": 13,
  "brit rock": 56,
  "showtunes": 20,
  "60s": 180,
  "ska": 31,
  "Brutal Death Metal": 12,
  "dance pop": 38,
  "Czech Republic": 16,
  "Protopunk": 11,
  "divas": 11,
  "rock'n'roll": 11,
  "independent": 11,
  "singer songwriter": 56,
  "dark ambient": 12,
  "industrial": 36,
  "russian": 20,
  "Blue-Eyed Soul": 24,
  "party": 34,
  "swedish": 19,
  "pop punk": 27,
  "experimental": 236,
  "hot": 33,
  "UK": 307,
  "bitch": 12,
  "20th Century": 16,
  "hardcore": 32,
  "Drum and bass": 19,
  "male": 72,
  "latino": 16,
  "blues rock": 65,
  "kgrl": 14,
  "Post-punk revival": 26,
  "francophone": 12,
  "rhythm and blues": 87,
  "Psychedelia": 12,
  "glasgow": 12,
  "Girl Groups": 21,
  "accordion": 11,
  "indie": 615,
  "punk rock": 120,
  "instrumental": 130,
  "melodic": 18,
  "easy listening": 195,
  "80s": 335,
  "duets": 18,
  "jazz fusion": 12,
  "British Girls": 11,
  "french": 48,
  "noise pop": 11,
  "goth": 22,
  "art pop": 27,
  "noise": 25,
  "psychedelic pop": 27,
  "alt country": 15,
  "texas": 16,
  "jazz": 320,
  "duo": 15,
  "garage": 30,
  "Stoner Rock": 17,
  "camp": 14,
  "female artists": 73,
  "Sweeney Todd": 14,
  "romantic": 74,
  "indie folk": 66,
  "latin jazz": 11,
  "electro-pop": 19,
  "Favorite": 100,
  "crooner": 15,
  "irish": 34,
  "Europe": 15,
  "jazz piano": 15,
  "Pop-Rock": 128,
  "girl band": 11,
  "folk rock": 143,
  "Singer/Songwriter": 16,
  "r and b": 32,
  "country": 93,
  "tarantino": 11,
  "Europop": 21,
  "melancholy": 91,
  "classique": 14,
  "golden oldies": 17,
  "female fronted": 14,
  "symphonic": 12,
  "love songs": 15,
  "alternative dance": 26,
  "jecks": 19,
  "fandom: greysanatomy": 13,
  "acoustic": 281,
  "dance-pop": 60,
  "latin": 44,
  "Klassik": 21,
  "eighties": 17,
  "Chanson Fran\u00e7aise": 12,
  "norwegian": 24,
  "baroque pop": 43,
  "singer-songwriters": 50,
  "favourite": 34,
  "piano rock": 25,
  "san francisco": 11,
  "german": 34,
  "psychedelic": 142,
  "1980s": 26,
  "cover": 19,
  "Electro Pop": 24,
  "My Favorites": 16,
  "40s": 28,
  "electro": 123,
  "indietronica": 31,
  "Broadway": 31,
  "30s": 15,
  "eclectic": 19,
  "electropop": 100,
  "neoclassical": 17,
  "groove": 36,
  "lesser known yet streamable artists": 29,
  "movie score composers": 17,
  "Grunge": 51,
  "new york": 76,
  "Aussie": 14,
  "shit": 17,
  "epic": 19,
  "female singers": 20,
  "melancholic": 55,
  "Lo-Fi": 69,
  "germany": 23,
  "lovely": 34,
  "sad": 29,
  "female singer-songwriter": 26,
  "classical music": 24,
  "folk pop": 14,
  "country rock": 28,
  "dance": 302,
  "chamber pop": 36,
  "alternative": 706,
  "sexy": 146,
  "minimal": 15,
  "Psychedelic Rock": 77,
  "liverpool": 22,
  "Scottish": 35,
  "sensual": 11,
  "Experimental Rock": 41,
  "Favorite Artists": 47,
  "male vocalists": 481,
  "ambient": 149,
  "Funk Rock": 13,
  "poetry": 19,
  "album rock": 18,
  "dark": 41,
  "ireland": 21,
  "r'n'b": 16,
  "swing": 48,
  "composer": 65,
  "1960s": 20,
  "Post punk": 45,
  "Ballad": 38,
  "Avant-Garde": 75,
  "alternative country": 15,
  "classic": 126,
  "10s": 25,
  "breakbeat": 18,
  "happy": 45,
  "NYC": 18,
  "garage rock revival": 17,
  "Jazz Divas": 12,
  "world": 79,
  "new romantic": 43,
  "spanish": 26,
  "greys anatomy": 29,
  "orchestral": 31,
  "theatrical": 11,
  "ethnic": 12,
  "to check out": 16,
  "songwriter": 49,
  "movie": 12,
  "black metal": 15,
  "Romantic Classical": 12,
  "Musical theatre": 11,
  "Gothic Rock": 16,
  "dark cabaret": 22,
  "european": 31,
  "trip hop": 33,
  "Traditional Pop": 15,
  "Pop-punk": 11,
  "heavy metal": 32,
  "Neo-Psychedelia": 21,
  "albums I own": 12,
  "Guilty Pleasures": 31,
  "diva": 75,
  "Retro": 44,
  "The Beatles": 19,
  "political": 31,
  "art rock": 71,
  "detroit": 19,
  "Grey's Anatomy": 29,
  "synth-pop": 32,
  "english": 262,
  "christmas": 23,
  "folk": 362,
  "60s pop": 16,
  "Manchester": 21,
  "gay": 96,
  "under 2000 listeners": 12,
  "pop rock": 301,
  "one hit wonder": 15,
  "americana": 66,
  "classic rock": 347,
  "relaxing": 36,
  "90s": 396,
  "favourite artists": 24,
  "Smooth Jazz": 56,
  "cool": 66,
  "want to see live": 21,
  "duet": 22,
  "summer": 13,
  "trance": 38,
  "the ladies that should sit on my sofa or somewhere else in my flat because they are darlings and oh so lovely": 12,
  "chick rock": 11,
  "norsk": 11,
  "Favourites": 88,
  "alternative metal": 17,
  "relax": 50,
  "Dead": 16,
  "New Weird America": 17,
  "twee": 17,
  "movie soundtrack": 14,
  "groovy": 19,
  "old school": 14,
  "Dreamy": 21,
  "mexico": 12,
  "guilty pleasure": 38,
  "mod": 13,
  "group": 14,
  "rnb": 129,
  "singer-songwriter": 517,
  "Supergroup": 11,
  "beautiful": 159,
  "80s Pop": 45,
  "noise rock": 12,
  "british": 363,
  "80's": 76,
  "acid jazz": 37,
  "ethereal": 26,
  "teen pop": 16,
  "quirky": 47,
  "Espanol": 12,
  "new age": 25,
  "queer": 58,
  "avantgarde": 31,
  "proto punk": 15,
  "Big Band": 24,
  "eurodance": 24,
  "film music": 24,
  "cz": 12,
  "opera": 31,
  "Rock and Roll": 62,
  "Alternative Folk": 15,
  "crooners": 15,
  "sweet": 33,
  "blues-rock": 21,
  "Scandinavian Girls": 11,
  "Britrock": 32,
  "power pop": 59,
  "oldies": 224,
  "contemporary folk": 20,
  "hippie": 17,
  "club": 34,
  "USA": 341,
  "college rock": 31,
  "indie pop": 299,
  "scotland": 26,
  "Brit": 14,
  "catchy": 25,
  "chanson francaise": 19,
  "electronic": 423,
  "70's": 29,
  "Neo Soul": 15,
  "00s": 513,
  "reggae": 35,
  "shoegaze": 34,
  "Asian": 13,
  "london": 87,
  "Standards": 17,
  "metal": 95,
  "brilliant": 15,
  "score": 27,
  "francais": 17,
  "british invasion": 21,
  "girl group": 18,
  "chillout": 295,
  "hip hop": 59,
  "best": 12,
  "World Music": 43,
  "adult contemporary": 54,
  "done": 12,
  "musical": 54,
  "atmospheric": 35,
  "glam rock": 59,
  "Mellow": 203,
  "space rock": 22,
  "music": 19,
  "nu jazz": 16,
  "Progressive rock": 115,
  "beatles": 20,
  "australia": 20,
  "chicago": 18,
  "misc": 11,
  "james bond": 12,
  "All": 199,
  "Eurovision": 11,
  "madchester": 11,
  "rock": 789,
  "jazz vocal": 52,
  "gospel": 18,
  "Alt-country": 69,
  "female vocalists": 444,
  "seen live": 761,
  "sex": 14,
  "jazz vocals": 12,
  "anti-folk": 11,
  "cabaret": 49,
  "vocalist": 12,
  "House": 83,
  "Electroclash": 22,
  "cute": 27,
  "solo": 11,
  "Great Lyricists": 40,
  "emotional": 11,
  "blues": 216,
  "Bossa Nova": 17,
  "italian": 13,
  "Sweden": 19,
  "hiphop": 25,
  "synthpop": 101,
  "Norway": 15,
  "guitar": 132,
  "Energetic": 11,
  "england": 181,
  "britpop": 226,
  "1990s": 22,
  "interesting": 13,
  "covers": 15,
  "live": 22,
  "soft rock": 149,
  "idm": 19,
  "Adult Alternative": 35,
  "Recommended": 15,
  "darkwave": 21,
  "all things annoying in the world put together into one stupid bitch": 11,
  "punk": 231,
  "crossover": 16,
  "brit pop": 59,
  "United States": 18,
  "Progressive": 35,
  "post-punk": 154,
  "female vocals": 139,
  "2000s": 35,
  "film score": 18,
  "70s": 233,
  "classic soul": 11,
  "actress": 27,
  "los angeles": 22,
  "downtempo": 80,
  "urban": 47,
  "latin pop": 11,
  "traditional": 14,
  "rockabilly": 24,
  "riot grrrl": 16,
  "rock n roll": 58,
  "ost": 48,
  "guitar virtuoso": 14,
  "good": 21,
  "Country: USA": 12,
  "folk-rock": 65,
  "singer": 24,
  "american": 437,
  "psychedelic folk": 13,
  "California": 72,
  "Garage Rock": 55,
  "Indie-Rock": 11,
  "freak folk": 17,
  "alternative pop": 52,
  "smooth": 39,
  "beautiful voice": 13,
  "overrated": 11,
  "female singer-songwriters": 21,
  "amazing": 79,
  "new wave": 207,
  "favorites": 320,
  "violin": 14,
  "60's": 28,
  "20th Century Classical": 11,
  "Myjukebox": 25,
  "Awesome": 109,
  "france": 29,
  "female": 310,
  "Czech": 26,
  "deutsch": 15,
  "northern soul": 11,
  "Soundtracks": 59,
  "Crap": 19,
  "1970s": 15,
  "dj": 12,
  "chill out": 15,
  "post-rock": 53,
  "punk cabaret": 11,
  "emo": 130,
  "motown": 28,
  "90's": 15,
  "canada": 35,
  "techno": 66,
  "french pop": 15,
  "dream pop": 54,
  "calm": 14,
  "celtic": 18,
  "female vocalist": 325,
  "rap": 62,
  "screamo": 21,
  "funk": 153,
  "Canadian": 41,
  "soft": 29,
  "Disco": 106,
  "vocal": 129,
  "nordic": 11,
  "pop": 787,
  "seattle": 18,
  "proto-punk": 28,
  "hard rock": 135,
  "weird": 17,
  "god": 11,
  "alternative rock": 438,
  "comedy": 28,
  "Female Voices": 123,
  "powerpop": 13,
  "great voice": 15,
  "alternative rap": 11,
  "classic jazz": 13,
  "soul": 258,
  "synth pop": 78,
  "Acoustic Rock": 36,
  "musical theater": 12,
  "Michigan": 17,
  "spotify": 59,
  "Gothic": 39,
  "genius": 86,
  "girl power": 26,
  "favorit": 11,
  "british rock": 38,
  "glam": 48,
  "lesbian": 13,
  "vocal jazz": 65,
  "synth": 36,
  "chanson": 35,
  "baroque": 17,
  "dub": 23,
  "girls": 15,
  "funky": 66,
  "australian": 23,
  "jangle pop": 13,
  "roots rock": 12
}