{
  "jazz": 153,
  "japan": 12,
  "singer songwriter": 20,
  "glitch": 19,
  "Stoner Rock": 33,
  "urban": 34,
  "england": 75,
  "funky": 45,
  "old school": 30,
  "art rock": 63,
  "UK": 129,
  "Funk Rock": 19,
  "world": 38,
  "Garage Rock": 63,
  "party": 25,
  "screamo": 26,
  "quirky": 44,
  "instrumental": 98,
  "piano": 44,
  "pop punk": 26,
  "shoegaze": 46,
  "political": 39,
  "alternative hip hop": 12,
  "NYC": 26,
  "Recommended": 19,
  "rock n roll": 41,
  "fun": 77,
  "alternative hip-hop": 20,
  "1980s": 14,
  "psychedelic": 159,
  "celtic": 11,
  "Drum and bass": 22,
  "remix": 12,
  "metal": 128,
  "Garage Punk": 21,
  "old school rap": 11,
  "Classical": 35,
  "breaks": 14,
  "british": 151,
  "synth-pop": 18,
  "hip hop": 84,
  "minimal": 26,
  "seattle": 12,
  "dark ambient": 17,
  "80s": 233,
  "east coast rap": 18,
  "unique": 12,
  "folk rock": 89,
  "All": 142,
  "Electroclash": 43,
  "rap": 86,
  "pop rock": 86,
  "new romantic": 19,
  "surf rock": 14,
  "dub": 24,
  "americana": 50,
  "80's": 40,
  "skate punk": 11,
  "scandinavian": 14,
  "indie rock": 292,
  "Need to Rate": 17,
  "legend": 43,
  "happy": 27,
  "gay": 34,
  "indie electronic": 24,
  "chicago": 33,
  "emo": 109,
  "dream pop": 44,
  "Brooklyn": 15,
  "USA": 288,
  "Post punk": 62,
  "queer": 25,
  "alt rock": 14,
  "downtempo": 63,
  "r&b": 35,
  "Favourites": 45,
  "goth": 53,
  "New Weird America": 18,
  "Gothic Metal": 16,
  "Guilty Pleasures": 15,
  "dance-pop": 22,
  "alternative": 510,
  "cool": 33,
  "atmospheric": 44,
  "art punk": 14,
  "washington": 11,
  "contemporary classical": 12,
  "Neo-Soul": 14,
  "lounge": 36,
  "90's": 13,
  "psychedelic pop": 20,
  "doom metal": 12,
  "hiphop": 55,
  "classic": 50,
  "House": 65,
  "electro-industrial": 18,
  "dance-punk": 14,
  "poetry": 13,
  "United States": 13,
  "want to see live": 11,
  "country rock": 19,
  "australian": 17,
  "indie folk": 44,
  "french": 25,
  "chillout": 165,
  "Progressive": 45,
  "breakbeat": 29,
  "epic": 11,
  "60's": 16,
  "Female Voices": 24,
  "Energetic": 12,
  "electropunk": 11,
  "singer-songwriters": 16,
  "trance": 37,
  "noise": 79,
  "seen live": 568,
  "producer": 13,
  "alt country": 18,
  "baroque pop": 29,
  "Electro Pop": 19,
  "oldies": 82,
  "synth pop": 68,
  "dance": 178,
  "female": 87,
  "liverpool": 11,
  "industrial metal": 25,
  "ambient": 132,
  "freak folk": 16,
  "dark electro": 13,
  "idm": 57,
  "cyberpunk": 12,
  "Awesome": 111,
  "California": 70,
  "college rock": 34,
  "dance rock": 11,
  "Disco": 43,
  "underground rap": 15,
  "industrial rock": 32,
  "crossover": 11,
  "post rock": 39,
  "kickasstic": 15,
  "synth": 35,
  "funny": 27,
  "country": 52,
  "space rock": 22,
  "4ad": 13,
  "roots rock": 11,
  "hard rock": 108,
  "canada": 34,
  "alternative rock": 319,
  "Post-punk revival": 19,
  "slowcore": 17,
  "ninja tune": 11,
  "70s": 124,
  "favorites": 232,
  "techno": 92,
  "rock": 539,
  "funk": 122,
  "underground": 25,
  "guitar": 58,
  "abstract": 14,
  "Jazz Hop": 11,
  "female vocal": 23,
  "indie pop": 199,
  "female vocalist": 104,
  "new age": 17,
  "brit rock": 14,
  "batcave": 13,
  "trip hop": 23,
  "Rock and Roll": 49,
  "ethereal": 24,
  "dark": 49,
  "toronto": 11,
  "dj": 25,
  "london": 31,
  "ebm": 28,
  "female artists": 15,
  "Soundtrack": 92,
  "post-hardcore": 26,
  "Pop-Rock": 39,
  "favourite": 14,
  "punk": 245,
  "Psychedelia": 13,
  "alternative rap": 24,
  "Nu Metal": 13,
  "detroit": 15,
  "dance punk": 20,
  "beautiful": 66,
  "electronica": 245,
  "post-rock": 82,
  "sad": 22,
  "r and b": 17,
  "thrash metal": 20,
  "heavy metal": 51,
  "underground hip-hop": 32,
  "duyster": 15,
  "2000s": 17,
  "Love": 102,
  "Neo-Psychedelia": 24,
  "Great Lyricists": 31,
  "german": 22,
  "male": 14,
  "New York City": 17,
  "spotify": 42,
  "boston": 13,
  "ost": 18,
  "underrated": 15,
  "hardcore": 87,
  "mod": 12,
  "math rock": 17,
  "new wave": 176,
  "Gothic": 66,
  "melodic hardcore": 16,
  "genius": 62,
  "alternative pop": 17,
  "soft rock": 40,
  "vocal": 23,
  "turntablism": 20,
  "post-punk": 182,
  "underground hip hop": 19,
  "90s": 284,
  "beats": 20,
  "metalcore": 21,
  "composers": 13,
  "motown": 11,
  "new york": 75,
  "groove": 24,
  "brit pop": 16,
  "alternative dance": 19,
  "80s Pop": 18,
  "singer-songwriter": 217,
  "electronic": 363,
  "blues rock": 33,
  "Surf": 11,
  "Avant-Garde": 96,
  "easy listening": 39,
  "electro": 140,
  "amazing": 31,
  "60s": 78,
  "twee": 17,
  "humor": 14,
  "Michigan": 11,
  "pop": 400,
  "post hardcore": 18,
  "glam rock": 33,
  "garage": 35,
  "elektro": 14,
  "punk rock": 137,
  "death metal": 22,
  "Pop-punk": 13,
  "prog": 13,
  "synthpop": 89,
  "avantgarde": 34,
  "good": 15,
  "art pop": 11,
  "rhythm and blues": 44,
  "acid jazz": 24,
  "composer": 22,
  "acoustic": 110,
  "lesser known yet streamable artists": 19,
  "blues": 105,
  "darkwave": 49,
  "jazzy": 11,
  "electro-pop": 18,
  "melancholy": 59,
  "japanese": 26,
  "reggae": 31,
  "ska punk": 15,
  "industrial": 94,
  "dark wave": 15,
  "sexy": 46,
  "chill": 101,
  "montreal": 11,
  "english": 116,
  "british rock": 11,
  "noise rock": 38,
  "dance pop": 13,
  "female fronted": 11,
  "Experimental Rock": 63,
  "soft": 13,
  "Progressive rock": 124,
  "relax": 15,
  "Retro": 13,
  "Favorite Artists": 38,
  "indie": 455,
  "france": 15,
  "folk": 196,
  "punkrock": 14,
  "ska": 29,
  "eclectic": 13,
  "electropop": 76,
  "Favorite": 74,
  "georgia": 14,
  "deathrock": 19,
  "noise pop": 28,
  "Gothic Rock": 41,
  "club": 22,
  "weird": 25,
  "rnb": 56,
  "rockabilly": 21,
  "Dreamy": 23,
  "songwriter": 17,
  "Post-Industrial": 11,
  "hardcore rap": 12,
  "black metal": 13,
  "glam": 20,
  "Gangsta Rap": 16,
  "pay attention": 15,
  "Officially Shit": 11,
  "power pop": 38,
  "britpop": 89,
  "spoken word": 15,
  "british invasion": 11,
  "instrumental hip-hop": 11,
  "east coast hip-hop": 17,
  "texas": 12,
  "soul": 109,
  "smooth": 15,
  "Mellow": 111,
  "alternative metal": 26,
  "goth rock": 25,
  "experimental": 288,
  "riot grrrl": 17,
  "Progressive metal": 17,
  "Indie-Rock": 12,
  "male vocalist": 45,
  "emusic": 14,
  "classic rock": 196,
  "1960s": 11,
  "Grunge": 60,
  "female vocalists": 165,
  "melancholic": 30,
  "Hip-Hop": 120,
  "nu jazz": 12,
  "folk-rock": 38,
  "Neo Soul": 12,
  "Psychedelic Rock": 68,
  "male vocalists": 263,
  "Jam": 12,
  "germany": 13,
  "check out": 34,
  "Canadian": 43,
  "Alt-country": 66,
  "World Music": 25,
  "los angeles": 32,
  "latin": 13,
  "Soundtracks": 19,
  "comedy": 28,
  "Fusion": 26,
  "East Coast": 18,
  "chamber pop": 20,
  "Real hip-hop": 14,
  "Punk-Rock": 14,
  "1990s": 14,
  "Lo-Fi": 87,
  "post-grunge": 12,
  "Acoustic Rock": 14,
  "Illinois": 15,
  "american": 364,
  "melodic punk": 12,
  "female vocals": 50,
  "00s": 270,
  "acid house": 12,
  "indietronica": 48,
  "alternative country": 18,
  "relaxing": 12,
  "trip-hop": 94,
  "hardcore punk": 29,
  "proto-punk": 27
}