{
  "folk rock": 122, 
  "rap": 49, 
  "dance": 223, 
  "glam": 27, 
  "ost": 27, 
  "Nu-metal": 26, 
  "heavy metal": 120, 
  "NYC": 31, 
  "shoegazer": 26, 
  "classic rock": 291, 
  "alternative rock": 687, 
  "turkish": 30, 
  "glam rock": 39, 
  "Lo-Fi": 178, 
  "Canadian": 78, 
  "piano rock": 23, 
  "speed metal": 16, 
  "seen live": 986, 
  "cool": 68, 
  "scandinavia": 13, 
  "art pop": 18, 
  "noise pop": 54, 
  "art punk": 28, 
  "no wave": 15, 
  "deutsch": 24, 
  "alternative country": 19, 
  "goth": 63, 
  "quebec": 12, 
  "download": 15, 
  "10s": 15, 
  "John Peel": 15, 
  "Norway": 19, 
  "folk": 335, 
  "90s": 372, 
  "art-rock": 13, 
  "Neo-Psychedelia": 51, 
  "indie rock": 661, 
  "chicago": 19, 
  "british rock": 36, 
  "post-rock": 222, 
  "new": 21, 
  "Funk Rock": 15, 
  "melancholy": 108, 
  "christian": 35, 
  "oldies": 70, 
  "groove metal": 21, 
  "french": 31, 
  "female singer-songwriter": 15, 
  "fun": 105, 
  "indie pop": 451, 
  "screamo": 69, 
  "trip-hop": 139, 
  "legend": 30, 
  "asciiecho": 18, 
  "melancholic": 83, 
  "Power metal": 19, 
  "great": 12, 
  "weird": 38, 
  "montreal": 17, 
  "trip hop": 46, 
  "glitch": 25, 
  "2000s": 24, 
  "composer": 27, 
  "san francisco": 14, 
  "brit pop": 45, 
  "goth rock": 24, 
  "catchy": 26, 
  "duyster": 50, 
  "france": 17, 
  "funky": 31, 
  "live": 20, 
  "music": 12, 
  "calm": 25, 
  "ambient pop": 13, 
  "australian": 26, 
  "indie electronic": 49, 
  "chillout": 303, 
  "sub pop": 12, 
  "indiepop": 17, 
  "relax": 32, 
  "club": 15, 
  "instrumental": 167, 
  "melodic metal": 29, 
  "folktronica": 19, 
  "Electro Pop": 24, 
  "grindcore": 18, 
  "soul": 72, 
  "female artists": 25, 
  "dark ambient": 34, 
  "metalcore": 65, 
  "male": 27, 
  "beautiful": 131, 
  "indie": 811, 
  "florida": 11, 
  "darkwave": 67, 
  "1980s": 11, 
  "Avant-Garde": 134, 
  "Post-Metal": 11, 
  "singer songwriter": 31, 
  "swedish": 43, 
  "winter": 11, 
  "dark wave": 17, 
  "90s Rock": 20, 
  "Need to Rate": 13, 
  "poetry": 12, 
  "lounge": 59, 
  "Stoner Rock": 43, 
  "amazing": 81, 
  "old school": 14, 
  "Dreamy": 40, 
  "comedy": 18, 
  "punk rock": 246, 
  "Turkish Pop": 14, 
  "funny": 17, 
  "experimental metal": 14, 
  "trash metal": 13, 
  "ethnic": 15, 
  "psychedelic": 254, 
  "All": 175, 
  "folk-rock": 48, 
  "Psychedelic Rock": 118, 
  "jungle": 11, 
  "emocore": 43, 
  "cute": 27, 
  "new rave": 31, 
  "london": 68, 
  "japan": 12, 
  "instrumental rock": 19, 
  "not emo": 22, 
  "Old School Punk": 14, 
  "Indietronic": 27, 
  "interesting": 14, 
  "baroque pop": 42, 
  "Fusion": 28, 
  "electropunk": 21, 
  "chill out": 19, 
  "texas": 21, 
  "good": 23, 
  "songwriter": 27, 
  "space rock": 56, 
  "eclectic": 18, 
  "listen to": 12, 
  "Favourites": 103, 
  "Bittersweet": 15, 
  "post-grunge": 59, 
  "electro punk": 12, 
  "rock": 959, 
  "77 punk": 13, 
  "european": 23, 
  "Garage Punk": 20, 
  "england": 147, 
  "Retro": 20, 
  "portland": 12, 
  "alt country": 17, 
  "canada": 63, 
  "British Punk": 21, 
  "space": 12, 
  "electronica": 387, 
  "electronic rock": 21, 
  "hardcore punk": 43, 
  "sadcore": 18, 
  "Drum and bass": 18, 
  "Pop-punk": 41, 
  "Doom": 15, 
  "riot grrrl": 26, 
  "dreampop": 12, 
  "bass": 11, 
  "postpunk": 11, 
  "70s": 120, 
  "United States": 18, 
  "techno": 79, 
  "dance-punk": 39, 
  "chamber pop": 51, 
  "finland": 14, 
  "punk": 442, 
  "british": 309, 
  "Gothic Metal": 30, 
  "american": 476, 
  "punkrock": 13, 
  "Gothic": 93, 
  "swing": 12, 
  "industrial": 125, 
  "favorites": 387, 
  "americana": 65, 
  "to check out": 18, 
  "post hardcore": 34, 
  "ethereal": 40, 
  "spanish": 13, 
  "hard rock": 231, 
  "electronic": 562, 
  "emusic": 23, 
  "lo fi": 14, 
  "pop rock": 212, 
  "new york": 74, 
  "canadian indie": 17, 
  "acid jazz": 27, 
  "twee pop": 23, 
  "movie score composers": 14, 
  "listen": 19, 
  "tooth and nail": 11, 
  "trippy": 19, 
  "japanese": 30, 
  "nu jazz": 16, 
  "World Music": 18, 
  "Britrock": 51, 
  "great lyrics": 11, 
  "toronto": 12, 
  "electro-pop": 20, 
  "christian rock": 31, 
  "Love": 179, 
  "triphop": 11, 
  "Classical": 48, 
  "death metal": 72, 
  "vocal": 29, 
  "scandinavian": 63, 
  "alternative metal": 71, 
  "happy": 51, 
  "seen in concert": 17, 
  "Experimental Rock": 121, 
  "melodic": 18, 
  "live gesehen": 15, 
  "bands ive seen live": 14, 
  "garage rock revival": 27, 
  "boston": 11, 
  "crossover": 23, 
  "gentle": 14, 
  "indie-pop": 13, 
  "seen": 14, 
  "britpop": 198, 
  "trance": 36, 
  "scotland": 27, 
  "post-punk": 312, 
  "Alt-country": 100, 
  "Pop-Rock": 82, 
  "iceland": 26, 
  "hiphop": 12, 
  "electropop": 89, 
  "germany": 31, 
  "Disco": 32, 
  "Hip-Hop": 94, 
  "Energetic": 15, 
  "electro rock": 20, 
  "breakcore": 14, 
  "downbeat": 11, 
  "Post punk": 124, 
  "metal": 286, 
  "los angeles": 25, 
  "80's": 27, 
  "Acid": 11, 
  "favourite artists": 19, 
  "stoner": 12, 
  "SXSW2007": 12, 
  "pay attention": 16, 
  "dance punk": 44, 
  "german": 49, 
  "Smooth Jazz": 11, 
  "twee": 44, 
  "black metal": 41, 
  "post rock": 109, 
  "90's": 21, 
  "queer": 26, 
  "Turkce": 11, 
  "Acoustic Rock": 31, 
  "Officially Shit": 14, 
  "slow": 18, 
  "dance rock": 26, 
  "deathrock": 11, 
  "rock n roll": 44, 
  "Southern Rock": 13, 
  "score": 17, 
  "pretty": 12, 
  "piano": 63, 
  "Melodic Death Metal": 33, 
  "Classic Punk": 17, 
  "Progressive": 115, 
  "indie-folk": 16, 
  "jazz": 169, 
  "Favorite": 135, 
  "neoclassical": 18, 
  "singer-songwriter": 333, 
  "breakbeat": 23, 
  "neofolk": 16, 
  "check later": 12, 
  "futurepop": 13, 
  "emo": 255, 
  "investigate": 12, 
  "Manchester": 24, 
  "hip hop": 38, 
  "Female Voices": 40, 
  "60's": 11, 
  "ebm": 34, 
  "sex": 14, 
  "new wave": 262, 
  "Recommended": 22, 
  "cyberpunk": 12, 
  "psychedelic folk": 16, 
  "Post Grunge": 20, 
  "Kiwi": 13, 
  "Garage Rock": 104, 
  "alternative pop": 47, 
  "Grunge": 113, 
  "want to see live": 44, 
  "New York City": 12, 
  "genius": 67, 
  "Berlin": 11, 
  "Electroclash": 55, 
  "Mellow": 203, 
  "Psychedelia": 17, 
  "glasgow": 18, 
  "latin": 14, 
  "spotify": 51, 
  "guitar": 102, 
  "77 style punk": 11, 
  "country": 66, 
  "quiet": 15, 
  "singer-songwriters": 18, 
  "Progressive metal": 71, 
  "experimental": 501, 
  "pop punk": 71, 
  "sweet": 20, 
  "alternative pop-rock": 12, 
  "pop": 654, 
  "sexy": 74, 
  "synth rock": 14, 
  "noise rock": 79, 
  "turkey": 18, 
  "Rock and Roll": 50, 
  "duo": 14, 
  "dub": 37, 
  "rapcore": 13, 
  "political": 43, 
  "under 2000 listeners": 25, 
  "Brooklyn": 15, 
  "California": 87, 
  "ireland": 15, 
  "synth": 56, 
  "upbeat": 11, 
  "lovely": 15, 
  "new metal": 12, 
  "relaxing": 27, 
  "drugs": 11, 
  "orchestral": 23, 
  "soft rock": 67, 
  "Soundtracks": 19, 
  "industrial rock": 39, 
  "hardcore": 166, 
  "sad": 29, 
  "funk": 89, 
  "chill": 180, 
  "georgia": 13, 
  "atmospheric": 92, 
  "powerpop": 31, 
  "tribal": 13, 
  "male vocalist": 63, 
  "thrash": 17, 
  "50s": 17, 
  "<3": 12, 
  "00s": 513, 
  "ambient": 267, 
  "seattle": 27, 
  "doom metal": 24, 
  "alternative dance": 25, 
  "synthpop": 109, 
  "80s": 254, 
  "party": 18, 
  "electro": 197, 
  "turkish rock": 17, 
  "independent": 12, 
  "indie folk": 95, 
  "norwegian": 24, 
  "rockabilly": 20, 
  "darker than the deepest sea": 20, 
  "freak folk": 34, 
  "celtic": 17, 
  "Post-punk revival": 64, 
  "kickasstic": 16, 
  "Female fronted metal": 13, 
  "college rock": 45, 
  "punk pop": 13, 
  "synth pop": 69, 
  "drone": 30, 
  "nordic": 17, 
  "english": 200, 
  "film music": 15, 
  "Progressive rock": 240, 
  "Nu Metal": 45, 
  "summer": 17, 
  "madchester": 11, 
  "jazz fusion": 12, 
  "melodic hardcore": 21, 
  "postrock": 22, 
  "power pop": 95, 
  "psych": 14, 
  "Favourite bands": 28, 
  "Aussie": 14, 
  "alternative": 920, 
  "folk noir": 12, 
  "New Zealand": 13, 
  "icelandic": 31, 
  "Electro-Rock": 17, 
  "art rock": 133, 
  "easy listening": 67, 
  "Soundtrack": 107, 
  "ska": 42, 
  "new romantic": 11, 
  "australia": 22, 
  "psychedelic pop": 26, 
  "rnb": 20, 
  "dark": 97, 
  "proto-punk": 25, 
  "electro-industrial": 24, 
  "world": 50, 
  "Fuck Off": 11, 
  "unique": 14, 
  "symphonic metal": 14, 
  "moody": 17, 
  "country rock": 22, 
  "Great Lyricists": 35, 
  "female vocals": 87, 
  "finnish": 18, 
  "free jazz": 13, 
  "jangle pop": 12, 
  "garage": 54, 
  "Sludge": 14, 
  "soft": 34, 
  "blues-rock": 11, 
  "female vocalist": 157, 
  "Punk-Rock": 28, 
  "lesser known yet streamable artists": 33, 
  "composers": 23, 
  "modern rock": 18, 
  "contemporary classical": 22, 
  "shoegaze": 143, 
  "female vocalists": 251, 
  "Bands I have seen live": 13, 
  "prog": 25, 
  "epic": 32, 
  "minimal": 39, 
  "noise": 128, 
  "Scottish": 31, 
  "avantgarde": 47, 
  "Adult Alternative": 18, 
  "Sweden": 37, 
  "acoustic": 208, 
  "downtempo": 111, 
  "cabaret": 12, 
  "folk metal": 12, 
  "prog rock": 20, 
  "krautrock": 22, 
  "check out": 72, 
  "slowcore": 51, 
  "idm": 72, 
  "UK": 275, 
  "Gothic Rock": 49, 
  "synth-pop": 15, 
  "Favorite Artists": 49, 
  "male vocalists": 465, 
  "washington": 17, 
  "british invasion": 11, 
  "thrash metal": 51, 
  "female": 128, 
  "1990s": 19, 
  "math rock": 41, 
  "new jersey": 12, 
  "quirky": 47, 
  "to listen": 16, 
  "industrial metal": 44, 
  "nu rave": 13, 
  "Indie-Rock": 37, 
  "dark electro": 23, 
  "romantic": 18, 
  "brit rock": 67, 
  "House": 54, 
  "Awesome": 197, 
  "smooth": 19, 
  "us": 11, 
  "Brit": 16, 
  "emotional": 18, 
  "avant garde": 15, 
  "Favorite Bands": 19, 
  "irish": 25, 
  "USA": 396, 
  "classic": 46, 
  "abstract": 15, 
  "disco punk": 12, 
  "Avant-garde Metal": 14, 
  "beats": 12, 
  "mathcore": 11, 
  "New Weird America": 37, 
  "blues": 121, 
  "shit": 16, 
  "gay": 37, 
  "blues rock": 52, 
  "dream pop": 108, 
  "new age": 20, 
  "nz": 13, 
  "female vocal": 36, 
  "rhythm and blues": 16, 
  "reggae": 28, 
  "60s": 69, 
  "favourite": 36, 
  "Post-Industrial": 14, 
  "post-hardcore": 61, 
  "Alternative Folk": 15, 
  "alt rock": 43, 
  "4ad": 13, 
  "female fronted": 20, 
  "indietronica": 113, 
  "Swedish Metal": 16, 
  "Sleep": 11, 
  "underrated": 24, 
  "film score": 12
}